[
  {
    "startTime": 1.4,
    "endTime": 3.04,
    "text": "one of the odder phenomena of"
  },
  {
    "startTime": 3.04,
    "endTime": 5.52,
    "text": "relationships is the immediate certainty"
  },
  {
    "startTime": 5.52,
    "endTime": 7.12,
    "text": "that whenever things go wrong in our"
  },
  {
    "startTime": 7.12,
    "endTime": 9.719,
    "text": "lives it is first and foremost and quite"
  },
  {
    "startTime": 9.719,
    "endTime": 13.0,
    "text": "obviously our partner's fault we get"
  },
  {
    "startTime": 13.0,
    "endTime": 15.04,
    "text": "furious with our partners because we"
  },
  {
    "startTime": 15.04,
    "endTime": 17.0,
    "text": "assign them such a deep role in our"
  },
  {
    "startTime": 17.0,
    "endTime": 19.84,
    "text": "lives we have faith that a person who"
  },
  {
    "startTime": 19.84,
    "endTime": 22.199,
    "text": "understands obscure parts of us whose"
  },
  {
    "startTime": 22.199,
    "endTime": 24.84,
    "text": "presence solves so many of our problems"
  },
  {
    "startTime": 24.84,
    "endTime": 27.24,
    "text": "couldn't realistically also be someone"
  },
  {
    "startTime": 27.24,
    "endTime": 29.4,
    "text": "who wouldn't be able to fix our whole"
  },
  {
    "startTime": 29.4,
    "endTime": 32.96,
    "text": "lives we exaggerate our partner's Powers"
  },
  {
    "startTime": 32.96,
    "endTime": 35.399,
    "text": "an exaggeration that's an echo heard in"
  },
  {
    "startTime": 35.399,
    "endTime": 38.32,
    "text": "adult life down the Decades of a childs"
  },
  {
    "startTime": 38.32,
    "endTime": 41.44,
    "text": "or at their parents the partner inherits"
  },
  {
    "startTime": 41.44,
    "endTime": 44.12,
    "text": "a little of that beautiful romantic"
  },
  {
    "startTime": 44.12,
    "endTime": 46.68,
    "text": "dangerous unfair trust that we as"
  },
  {
    "startTime": 46.68,
    "endTime": 49.64,
    "text": "children once had in our parents at one"
  },
  {
    "startTime": 49.64,
    "endTime": 51.48,
    "text": "level the lover has learned how to"
  },
  {
    "startTime": 51.48,
    "endTime": 54.719,
    "text": "reassure the anxious child in us that's"
  },
  {
    "startTime": 54.719,
    "endTime": 56.84,
    "text": "why we love them but that source of"
  },
  {
    "startTime": 56.84,
    "endTime": 59.28,
    "text": "strength also brings with it some very"
  },
  {
    "startTime": 59.28,
    "endTime": 61.84,
    "text": "serious problem s for the Primitive part"
  },
  {
    "startTime": 61.84,
    "endTime": 64.72,
    "text": "of us insists on trusting them a little"
  },
  {
    "startTime": 64.72,
    "endTime": 67.0,
    "text": "too much believing that they actually"
  },
  {
    "startTime": 67.0,
    "endTime": 69.84,
    "text": "control far more of existence than they"
  },
  {
    "startTime": 69.84,
    "endTime": 71.759,
    "text": "possibly"
  },
  {
    "startTime": 71.759,
    "endTime": 74.4,
    "text": "could it's also to do with a permission"
  },
  {
    "startTime": 74.4,
    "endTime": 77.159,
    "text": "that the partner's love gives us to moan"
  },
  {
    "startTime": 77.159,
    "endTime": 79.84,
    "text": "in a way we cannot otherwise the world"
  },
  {
    "startTime": 79.84,
    "endTime": 82.64,
    "text": "is constantly mean to us it rejects our"
  },
  {
    "startTime": 82.64,
    "endTime": 84.84,
    "text": "creative Endeavors it overlooks Us in"
  },
  {
    "startTime": 84.84,
    "endTime": 88.04,
    "text": "promotions it rewards idiots but usually"
  },
  {
    "startTime": 88.04,
    "endTime": 90.759,
    "text": "we can't complain we we can't get angry"
  },
  {
    "startTime": 90.759,
    "endTime": 92.56,
    "text": "with the people who are really to blame"
  },
  {
    "startTime": 92.56,
    "endTime": 95.6,
    "text": "for hurting us so we get angry with"
  },
  {
    "startTime": 95.6,
    "endTime": 97.88,
    "text": "those whom we can be sure will tolerate"
  },
  {
    "startTime": 97.88,
    "endTime": 100.32,
    "text": "us for blaming them we get angry with"
  },
  {
    "startTime": 100.32,
    "endTime": 103.36,
    "text": "the very nicest most sympathetic most"
  },
  {
    "startTime": 103.36,
    "endTime": 106.04,
    "text": "loyal people in our vicinity the ones"
  },
  {
    "startTime": 106.04,
    "endTime": 108.68,
    "text": "least likely to have harmed us but most"
  },
  {
    "startTime": 108.68,
    "endTime": 111.0,
    "text": "likely to stick around while we blame"
  },
  {
    "startTime": 111.0,
    "endTime": 114.28,
    "text": "them furiously for having done so the"
  },
  {
    "startTime": 114.28,
    "endTime": 116.759,
    "text": "mean words and mad accusations we mutter"
  },
  {
    "startTime": 116.759,
    "endTime": 119.439,
    "text": "to our lovers undoubtedly often sound"
  },
  {
    "startTime": 119.439,
    "endTime": 120.399,
    "text": "horrible"
  },
  {
    "startTime": 120.399,
    "endTime": 121.96,
    "text": "but let's at least remember that they"
  },
  {
    "startTime": 121.96,
    "endTime": 124.719,
    "text": "are a curious proof of intimacy a"
  },
  {
    "startTime": 124.719,
    "endTime": 127.479,
    "text": "symptom of Love itself and in their own"
  },
  {
    "startTime": 127.479,
    "endTime": 130.8,
    "text": "way oddly romantic a detail indirectly"
  },
  {
    "startTime": 130.8,
    "endTime": 133.56,
    "text": "acknowledged by their frequently sexual"
  },
  {
    "startTime": 133.56,
    "endTime": 136.16,
    "text": "conclusions we can tell any stranger"
  },
  {
    "startTime": 136.16,
    "endTime": 138.76,
    "text": "something reasonable and polite but only"
  },
  {
    "startTime": 138.76,
    "endTime": 140.519,
    "text": "in the presence of someone we really"
  },
  {
    "startTime": 140.519,
    "endTime": 143.0,
    "text": "trust can we dare to be properly"
  },
  {
    "startTime": 143.0,
    "endTime": 145.319,
    "text": "irrational and truly"
  },
  {
    "startTime": 145.319,
    "endTime": 147.84,
    "text": "unkind if we think of love as being in"
  },
  {
    "startTime": 147.84,
    "endTime": 150.16,
    "text": "perfect agreement all the time we will"
  },
  {
    "startTime": 150.16,
    "endTime": 152.519,
    "text": "feel that getting into fights must mean"
  },
  {
    "startTime": 152.519,
    "endTime": 155.08,
    "text": "that a relationship is winding down or"
  },
  {
    "startTime": 155.08,
    "endTime": 158.2,
    "text": "starting to fall apart but crazy blame"
  },
  {
    "startTime": 158.2,
    "endTime": 160.879,
    "text": "games are at heart just a symptom of an"
  },
  {
    "startTime": 160.879,
    "endTime": 163.599,
    "text": "intensity of investment in another"
  },
  {
    "startTime": 163.599,
    "endTime": 166.319,
    "text": "person we aren't simply nice with our"
  },
  {
    "startTime": 166.319,
    "endTime": 168.72,
    "text": "partners because we're so close to them"
  },
  {
    "startTime": 168.72,
    "endTime": 171.68,
    "text": "they draw us into very private zones of"
  },
  {
    "startTime": 171.68,
    "endTime": 174.28,
    "text": "turbulence and distress from which"
  },
  {
    "startTime": 174.28,
    "endTime": 177.08,
    "text": "absolutely everyone else is excluded"
  },
  {
    "startTime": 177.08,
    "endTime": 179.04,
    "text": "that's one of the stranger more"
  },
  {
    "startTime": 179.04,
    "endTime": 181.879,
    "text": "unfortunate and yet from a calm angle"
  },
  {
    "startTime": 181.879,
    "endTime": 187.08,
    "text": "almost flattering Gifts of love"
  }
]