[
  {
    "startTime": 1.67,
    "endTime": 8.86,
    "text": "[Music]"
  },
  {
    "startTime": 11.5,
    "endTime": 13.719,
    "text": "[Music]"
  },
  {
    "startTime": 13.719,
    "endTime": 17.279,
    "text": "I want to start with a game okay and to"
  },
  {
    "startTime": 17.279,
    "endTime": 19.92,
    "text": "win this game all you have to do is see"
  },
  {
    "startTime": 19.92,
    "endTime": 22.039,
    "text": "the reality that's in front of you as it"
  },
  {
    "startTime": 22.039,
    "endTime": 24.279,
    "text": "really is all right so we have two"
  },
  {
    "startTime": 24.279,
    "endTime": 26.4,
    "text": "panels here of colored"
  },
  {
    "startTime": 26.4,
    "endTime": 30.24,
    "text": "dots and one of those dots is the same"
  },
  {
    "startTime": 30.24,
    "endTime": 31.439,
    "text": "in the two"
  },
  {
    "startTime": 31.439,
    "endTime": 34.6,
    "text": "panels okay and you have to tell me"
  },
  {
    "startTime": 34.6,
    "endTime": 37.719,
    "text": "which one now I'll narrow that down"
  },
  {
    "startTime": 37.719,
    "endTime": 40.8,
    "text": "to the gray one the green one and say"
  },
  {
    "startTime": 40.8,
    "endTime": 43.6,
    "text": "the orange one so by a show of hands"
  },
  {
    "startTime": 43.6,
    "endTime": 45.28,
    "text": "we'll start with the easiest one show of"
  },
  {
    "startTime": 45.28,
    "endTime": 46.559,
    "text": "hands how many people think it's the"
  },
  {
    "startTime": 46.559,
    "endTime": 47.84,
    "text": "gray"
  },
  {
    "startTime": 47.84,
    "endTime": 51.36,
    "text": "one really okay how many people think"
  },
  {
    "startTime": 51.36,
    "endTime": 53.879,
    "text": "it's the green"
  },
  {
    "startTime": 53.879,
    "endTime": 56.16,
    "text": "one and how many people think it's the"
  },
  {
    "startTime": 56.16,
    "endTime": 58.079,
    "text": "orange"
  },
  {
    "startTime": 58.079,
    "endTime": 61.64,
    "text": "one so pretty even split"
  },
  {
    "startTime": 61.64,
    "endTime": 64.96,
    "text": "so let's find out what the reality is"
  },
  {
    "startTime": 64.96,
    "endTime": 67.92,
    "text": "here is the orange"
  },
  {
    "startTime": 68.08,
    "endTime": 72.72,
    "text": "one right here's the green"
  },
  {
    "startTime": 72.72,
    "endTime": 77.2,
    "text": "one and here's the gray"
  },
  {
    "startTime": 79.24,
    "endTime": 81.759,
    "text": "one so for all of you saw that you're a"
  },
  {
    "startTime": 81.759,
    "endTime": 82.64,
    "text": "complete"
  },
  {
    "startTime": 82.64,
    "endTime": 85.32,
    "text": "realists all"
  },
  {
    "startTime": 85.32,
    "endTime": 87.68,
    "text": "right so this is pretty amazing actually"
  },
  {
    "startTime": 87.68,
    "endTime": 89.56,
    "text": "isn't it because nearly every living"
  },
  {
    "startTime": 89.56,
    "endTime": 92.52,
    "text": "system has evolved the ability to detect"
  },
  {
    "startTime": 92.52,
    "endTime": 94.72,
    "text": "light in one way or another so for us"
  },
  {
    "startTime": 94.72,
    "endTime": 96.96,
    "text": "seeing color is one of the simplest"
  },
  {
    "startTime": 96.96,
    "endTime": 98.96,
    "text": "things the brain does and yet even at"
  },
  {
    "startTime": 98.96,
    "endTime": 102.079,
    "text": "this most fundamental level context is"
  },
  {
    "startTime": 102.079,
    "endTime": 104.32,
    "text": "everything okay what I want to talk"
  },
  {
    "startTime": 104.32,
    "endTime": 106.759,
    "text": "about is not that context is everything"
  },
  {
    "startTime": 106.759,
    "endTime": 109.0,
    "text": "but why is context everything because"
  },
  {
    "startTime": 109.0,
    "endTime": 111.28,
    "text": "it's answering that question that tells"
  },
  {
    "startTime": 111.28,
    "endTime": 115.079,
    "text": "us not only why we see what we do but"
  },
  {
    "startTime": 115.079,
    "endTime": 116.759,
    "text": "who we are as individuals and who we are"
  },
  {
    "startTime": 116.759,
    "endTime": 118.68,
    "text": "as a"
  },
  {
    "startTime": 118.68,
    "endTime": 120.719,
    "text": "society but but first we have to ask"
  },
  {
    "startTime": 120.719,
    "endTime": 122.399,
    "text": "another question which is what is color"
  },
  {
    "startTime": 122.399,
    "endTime": 124.28,
    "text": "four and instead of telling you I'll"
  },
  {
    "startTime": 124.28,
    "endTime": 127.56,
    "text": "just show you what you see here is a"
  },
  {
    "startTime": 127.56,
    "endTime": 129.52,
    "text": "jungle scene and you see the surfaces"
  },
  {
    "startTime": 129.52,
    "endTime": 131.2,
    "text": "according to the amount of light that"
  },
  {
    "startTime": 131.2,
    "endTime": 133.56,
    "text": "those surfaces reflect now can any of"
  },
  {
    "startTime": 133.56,
    "endTime": 135.519,
    "text": "you see the Predator that's about to"
  },
  {
    "startTime": 135.519,
    "endTime": 137.879,
    "text": "jump out at you and if you haven't seen"
  },
  {
    "startTime": 137.879,
    "endTime": 141.8,
    "text": "it yet you're dead right can anyone see"
  },
  {
    "startTime": 141.8,
    "endTime": 145.08,
    "text": "it anyone no now let's see the surfaces"
  },
  {
    "startTime": 145.08,
    "endTime": 147.08,
    "text": "according to the quality of light that"
  },
  {
    "startTime": 147.08,
    "endTime": 150.04,
    "text": "they reflect and now you see it right"
  },
  {
    "startTime": 150.04,
    "endTime": 153.319,
    "text": "right so color enables us to see the"
  },
  {
    "startTime": 153.319,
    "endTime": 155.0,
    "text": "similarities and differences between"
  },
  {
    "startTime": 155.0,
    "endTime": 157.04,
    "text": "surfaces according to the full spectrum"
  },
  {
    "startTime": 157.04,
    "endTime": 158.68,
    "text": "of light that they reflect but what"
  },
  {
    "startTime": 158.68,
    "endTime": 161.04,
    "text": "you've just done is in many respects"
  },
  {
    "startTime": 161.04,
    "endTime": 162.239,
    "text": "mathematically"
  },
  {
    "startTime": 162.239,
    "endTime": 165.36,
    "text": "impossible why because as Barkley tells"
  },
  {
    "startTime": 165.36,
    "endTime": 167.319,
    "text": "us we have no direct access to our"
  },
  {
    "startTime": 167.319,
    "endTime": 169.239,
    "text": "physical world other than through our"
  },
  {
    "startTime": 169.239,
    "endTime": 171.68,
    "text": "senses and the light that falls onto our"
  },
  {
    "startTime": 171.68,
    "endTime": 173.72,
    "text": "eyes is determined by multiple things in"
  },
  {
    "startTime": 173.72,
    "endTime": 176.239,
    "text": "the world not only the color of objects"
  },
  {
    "startTime": 176.239,
    "endTime": 178.28,
    "text": "but also the color of their illumination"
  },
  {
    "startTime": 178.28,
    "endTime": 180.159,
    "text": "and the color of the space between us in"
  },
  {
    "startTime": 180.159,
    "endTime": 182.519,
    "text": "those objects you vary any one of those"
  },
  {
    "startTime": 182.519,
    "endTime": 184.84,
    "text": "parameters and you'll change the color"
  },
  {
    "startTime": 184.84,
    "endTime": 187.519,
    "text": "of the light that falls onto your"
  },
  {
    "startTime": 187.519,
    "endTime": 189.959,
    "text": "eye this is a huge problem because it"
  },
  {
    "startTime": 189.959,
    "endTime": 193.2,
    "text": "means that the same image could have an"
  },
  {
    "startTime": 193.2,
    "endTime": 195.159,
    "text": "infinite number of possible real world"
  },
  {
    "startTime": 195.159,
    "endTime": 197.64,
    "text": "sources so let me show you what I mean"
  },
  {
    "startTime": 197.64,
    "endTime": 199.04,
    "text": "imagine that this is the back of your"
  },
  {
    "startTime": 199.04,
    "endTime": 201.799,
    "text": "eye okay and these are two projections"
  },
  {
    "startTime": 201.799,
    "endTime": 204.2,
    "text": "from the world they're identical in"
  },
  {
    "startTime": 204.2,
    "endTime": 208.2,
    "text": "every single way identical in shape size"
  },
  {
    "startTime": 208.2,
    "endTime": 210.68,
    "text": "spectral content they are the same as"
  },
  {
    "startTime": 210.68,
    "endTime": 212.239,
    "text": "far as your eye is"
  },
  {
    "startTime": 212.239,
    "endTime": 215.12,
    "text": "concerned and yet they come from"
  },
  {
    "startTime": 215.12,
    "endTime": 217.519,
    "text": "completely different"
  },
  {
    "startTime": 217.519,
    "endTime": 221.56,
    "text": "sources the one on the right comes from"
  },
  {
    "startTime": 221.56,
    "endTime": 224.4,
    "text": "a yellow surface in Shadow oriented"
  },
  {
    "startTime": 224.4,
    "endTime": 227.36,
    "text": "facing the left viewed through a pinkish"
  },
  {
    "startTime": 227.36,
    "endTime": 230.4,
    "text": "medium the one on the left comes from an"
  },
  {
    "startTime": 230.4,
    "endTime": 233.159,
    "text": "orange surface under direct light facing"
  },
  {
    "startTime": 233.159,
    "endTime": 234.92,
    "text": "to the right viewed through a sort of a"
  },
  {
    "startTime": 234.92,
    "endTime": 237.0,
    "text": "bluish medium completely different"
  },
  {
    "startTime": 237.0,
    "endTime": 239.84,
    "text": "meanings giving rise to the exact same"
  },
  {
    "startTime": 239.84,
    "endTime": 242.159,
    "text": "name retinal information and yet it's"
  },
  {
    "startTime": 242.159,
    "endTime": 245.36,
    "text": "only the retinal information that we get"
  },
  {
    "startTime": 245.36,
    "endTime": 249.079,
    "text": "so how on Earth do we even see so if you"
  },
  {
    "startTime": 249.079,
    "endTime": 251.4,
    "text": "remember anything in this next 18"
  },
  {
    "startTime": 251.4,
    "endTime": 253.48,
    "text": "minutes remember this that the light"
  },
  {
    "startTime": 253.48,
    "endTime": 255.44,
    "text": "that falls onto your eye sensory"
  },
  {
    "startTime": 255.44,
    "endTime": 258.04,
    "text": "information is meaningless because it"
  },
  {
    "startTime": 258.04,
    "endTime": 260.6,
    "text": "could mean literally anything and what's"
  },
  {
    "startTime": 260.6,
    "endTime": 262.16,
    "text": "true for sensory information is true for"
  },
  {
    "startTime": 262.16,
    "endTime": 263.8,
    "text": "information generally there's no"
  },
  {
    "startTime": 263.8,
    "endTime": 265.56,
    "text": "inherent meaning in information it's"
  },
  {
    "startTime": 265.56,
    "endTime": 268.0,
    "text": "what we do with that information that"
  },
  {
    "startTime": 268.0,
    "endTime": 271.12,
    "text": "matters so how do we see see well we see"
  },
  {
    "startTime": 271.12,
    "endTime": 274.24,
    "text": "by learning to see so the brain evolved"
  },
  {
    "startTime": 274.24,
    "endTime": 276.36,
    "text": "the mechanisms for finding patterns"
  },
  {
    "startTime": 276.36,
    "endTime": 278.44,
    "text": "finding relationships and information"
  },
  {
    "startTime": 278.44,
    "endTime": 281.0,
    "text": "and associating those relationships with"
  },
  {
    "startTime": 281.0,
    "endTime": 283.919,
    "text": "a behavioral meaning a significance by"
  },
  {
    "startTime": 283.919,
    "endTime": 286.56,
    "text": "interacting with the world we're very"
  },
  {
    "startTime": 286.56,
    "endTime": 288.52,
    "text": "aware of this in the form of more"
  },
  {
    "startTime": 288.52,
    "endTime": 290.479,
    "text": "cognitive attributes like language so"
  },
  {
    "startTime": 290.479,
    "endTime": 291.4,
    "text": "I'm going to give you some letter"
  },
  {
    "startTime": 291.4,
    "endTime": 292.68,
    "text": "strings and I want you to read them out"
  },
  {
    "startTime": 292.68,
    "endTime": 296.4,
    "text": "for me if you can"
  },
  {
    "startTime": 300.479,
    "endTime": 302.36,
    "text": "what are youing what are you reading"
  },
  {
    "startTime": 302.36,
    "endTime": 304.56,
    "text": "half the letters are missing right"
  },
  {
    "startTime": 304.56,
    "endTime": 306.639,
    "text": "there's no a prior reason why an H has"
  },
  {
    "startTime": 306.639,
    "endTime": 308.88,
    "text": "to go between that W and a but you put"
  },
  {
    "startTime": 308.88,
    "endTime": 311.039,
    "text": "one there why because in the statistics"
  },
  {
    "startTime": 311.039,
    "endTime": 312.72,
    "text": "of your past experience it would have"
  },
  {
    "startTime": 312.72,
    "endTime": 315.639,
    "text": "been useful to do so so you do so again"
  },
  {
    "startTime": 315.639,
    "endTime": 317.28,
    "text": "and yet you don't put a letter after"
  },
  {
    "startTime": 317.28,
    "endTime": 319.4,
    "text": "that first T why because it would have"
  },
  {
    "startTime": 319.4,
    "endTime": 321.639,
    "text": "been useful in the past so you don't do"
  },
  {
    "startTime": 321.639,
    "endTime": 324.96,
    "text": "it again so let me show you how quickly"
  },
  {
    "startTime": 324.96,
    "endTime": 327.52,
    "text": "our brains can redefine normality even"
  },
  {
    "startTime": 327.52,
    "endTime": 329.0,
    "text": "at the simplest thing the brain does"
  },
  {
    "startTime": 329.0,
    "endTime": 330.52,
    "text": "which is color so if I could have the"
  },
  {
    "startTime": 330.52,
    "endTime": 333.4,
    "text": "lights down up here I want you to First"
  },
  {
    "startTime": 333.4,
    "endTime": 334.919,
    "text": "notice that those two desert scenes are"
  },
  {
    "startTime": 334.919,
    "endTime": 336.56,
    "text": "physically the same one is simply the"
  },
  {
    "startTime": 336.56,
    "endTime": 339.479,
    "text": "flipping of the other"
  },
  {
    "startTime": 339.479,
    "endTime": 342.84,
    "text": "okay now I want you to look at that dot"
  },
  {
    "startTime": 342.84,
    "endTime": 346.039,
    "text": "between the green and the red okay and I"
  },
  {
    "startTime": 346.039,
    "endTime": 347.479,
    "text": "want you to just stare at that dot don't"
  },
  {
    "startTime": 347.479,
    "endTime": 348.639,
    "text": "look anywhere else and we're going to"
  },
  {
    "startTime": 348.639,
    "endTime": 350.039,
    "text": "look at that for about 30 seconds which"
  },
  {
    "startTime": 350.039,
    "endTime": 352.88,
    "text": "is a bit of a killer in an 18-minute"
  },
  {
    "startTime": 352.88,
    "endTime": 355.88,
    "text": "talk okay but I really want you to learn"
  },
  {
    "startTime": 355.88,
    "endTime": 357.319,
    "text": "and I'll tell you don't look anywhere"
  },
  {
    "startTime": 357.319,
    "endTime": 359.24,
    "text": "else and I'll tell you what's happening"
  },
  {
    "startTime": 359.24,
    "endTime": 361.4,
    "text": "inside your head your brain is learning"
  },
  {
    "startTime": 361.4,
    "endTime": 362.88,
    "text": "and it's learning that the right side of"
  },
  {
    "startTime": 362.88,
    "endTime": 365.039,
    "text": "its visual field is under red"
  },
  {
    "startTime": 365.039,
    "endTime": 366.96,
    "text": "illumination the left side of its visual"
  },
  {
    "startTime": 366.96,
    "endTime": 368.68,
    "text": "field is under green illumination that's"
  },
  {
    "startTime": 368.68,
    "endTime": 369.599,
    "text": "what it's"
  },
  {
    "startTime": 369.599,
    "endTime": 373.039,
    "text": "learning okay now when I tell you I want"
  },
  {
    "startTime": 373.039,
    "endTime": 374.24,
    "text": "you to look at the dot between the two"
  },
  {
    "startTime": 374.24,
    "endTime": 375.16,
    "text": "desert"
  },
  {
    "startTime": 375.16,
    "endTime": 379.08,
    "text": "scenes so why don't you do that"
  },
  {
    "startTime": 380.72,
    "endTime": 383.919,
    "text": "now can we have the lights up again so I"
  },
  {
    "startTime": 383.919,
    "endTime": 385.199,
    "text": "take it from your response they don't"
  },
  {
    "startTime": 385.199,
    "endTime": 387.319,
    "text": "look the same anymore"
  },
  {
    "startTime": 387.319,
    "endTime": 390.479,
    "text": "right why because yourin is seeing that"
  },
  {
    "startTime": 390.479,
    "endTime": 392.919,
    "text": "same information as if the right one is"
  },
  {
    "startTime": 392.919,
    "endTime": 394.639,
    "text": "still under red light and the left one"
  },
  {
    "startTime": 394.639,
    "endTime": 396.16,
    "text": "is still under green light that's your"
  },
  {
    "startTime": 396.16,
    "endTime": 399.08,
    "text": "new normal okay so what does this mean"
  },
  {
    "startTime": 399.08,
    "endTime": 400.52,
    "text": "for context it means I can take these"
  },
  {
    "startTime": 400.52,
    "endTime": 402.56,
    "text": "two identical squares and I can put them"
  },
  {
    "startTime": 402.56,
    "endTime": 404.12,
    "text": "in light and dark surrounds now the one"
  },
  {
    "startTime": 404.12,
    "endTime": 405.52,
    "text": "on the dark surround looks lighter than"
  },
  {
    "startTime": 405.52,
    "endTime": 407.08,
    "text": "one the light surround What's"
  },
  {
    "startTime": 407.08,
    "endTime": 408.919,
    "text": "significant is not simply the light and"
  },
  {
    "startTime": 408.919,
    "endTime": 411.0,
    "text": "dark surrounds that matter it's what"
  },
  {
    "startTime": 411.0,
    "endTime": 412.639,
    "text": "those light and dark surrounds meant for"
  },
  {
    "startTime": 412.639,
    "endTime": 414.639,
    "text": "your behavior in the past so I'll show"
  },
  {
    "startTime": 414.639,
    "endTime": 416.84,
    "text": "you what I mean here we have that exact"
  },
  {
    "startTime": 416.84,
    "endTime": 419.599,
    "text": "same illusion we have two identical"
  },
  {
    "startTime": 419.599,
    "endTime": 421.56,
    "text": "tiles on the left one in a dark surround"
  },
  {
    "startTime": 421.56,
    "endTime": 423.0,
    "text": "one in a light surround and the same"
  },
  {
    "startTime": 423.0,
    "endTime": 424.84,
    "text": "thing over on the right now what I'm"
  },
  {
    "startTime": 424.84,
    "endTime": 426.36,
    "text": "going to do is I'm going to reveal those"
  },
  {
    "startTime": 426.36,
    "endTime": 428.28,
    "text": "two scenes but I'm not going to change"
  },
  {
    "startTime": 428.28,
    "endTime": 430.4,
    "text": "anything within those boxes except their"
  },
  {
    "startTime": 430.4,
    "endTime": 432.759,
    "text": "meaning and see what happens to your"
  },
  {
    "startTime": 432.759,
    "endTime": 435.319,
    "text": "perception notice that on the left the"
  },
  {
    "startTime": 435.319,
    "endTime": 437.639,
    "text": "two tiles look nearly completely"
  },
  {
    "startTime": 437.639,
    "endTime": 439.919,
    "text": "opposite one very white and one very"
  },
  {
    "startTime": 439.919,
    "endTime": 442.52,
    "text": "dark right whereas on the right the two"
  },
  {
    "startTime": 442.52,
    "endTime": 445.56,
    "text": "tiles look nearly the same and yet there"
  },
  {
    "startTime": 445.56,
    "endTime": 447.68,
    "text": "is still one on a dark shr and one on a"
  },
  {
    "startTime": 447.68,
    "endTime": 450.919,
    "text": "light roundr why because if the tile in"
  },
  {
    "startTime": 450.919,
    "endTime": 453.44,
    "text": "that shadow were in fact in Shadow and"
  },
  {
    "startTime": 453.44,
    "endTime": 455.039,
    "text": "reflecting the same amount of light to"
  },
  {
    "startTime": 455.039,
    "endTime": 457.599,
    "text": "your eye as the one outside the shadow"
  },
  {
    "startTime": 457.599,
    "endTime": 459.72,
    "text": "it would have to be more reflective just"
  },
  {
    "startTime": 459.72,
    "endTime": 461.84,
    "text": "the laws of physics so you see it that"
  },
  {
    "startTime": 461.84,
    "endTime": 464.24,
    "text": "way whereas on the right the information"
  },
  {
    "startTime": 464.24,
    "endTime": 466.44,
    "text": "is consistent with those two tiles being"
  },
  {
    "startTime": 466.44,
    "endTime": 468.52,
    "text": "under the same light if they're under"
  },
  {
    "startTime": 468.52,
    "endTime": 469.72,
    "text": "the same light reflecting the same"
  },
  {
    "startTime": 469.72,
    "endTime": 471.44,
    "text": "amount of light to your eye then they"
  },
  {
    "startTime": 471.44,
    "endTime": 473.639,
    "text": "must be equally reflective so you see it"
  },
  {
    "startTime": 473.639,
    "endTime": 476.24,
    "text": "that way which means we can bring all"
  },
  {
    "startTime": 476.24,
    "endTime": 477.84,
    "text": "this information together to create some"
  },
  {
    "startTime": 477.84,
    "endTime": 479.56,
    "text": "incredibly strong Illusions this is one"
  },
  {
    "startTime": 479.56,
    "endTime": 482.08,
    "text": "I made a few years ago and you'll notice"
  },
  {
    "startTime": 482.08,
    "endTime": 484.84,
    "text": "you see a dark brown tile at the top and"
  },
  {
    "startTime": 484.84,
    "endTime": 487.52,
    "text": "a bright orange tile at the side that is"
  },
  {
    "startTime": 487.52,
    "endTime": 489.36,
    "text": "your perceptual reality the physical"
  },
  {
    "startTime": 489.36,
    "endTime": 493.159,
    "text": "reality is that those two tiles are the"
  },
  {
    "startTime": 493.44,
    "endTime": 496.72,
    "text": "same here you see four gray tiles on"
  },
  {
    "startTime": 496.72,
    "endTime": 499.879,
    "text": "your left seven gray tiles on the right"
  },
  {
    "startTime": 499.879,
    "endTime": 501.36,
    "text": "I'm not going to change those Tiles at"
  },
  {
    "startTime": 501.36,
    "endTime": 502.84,
    "text": "all but I'm going to reveal the rest of"
  },
  {
    "startTime": 502.84,
    "endTime": 505.72,
    "text": "the scene and see what happens to your"
  },
  {
    "startTime": 505.72,
    "endTime": 508.28,
    "text": "perception the four blue tiles on the"
  },
  {
    "startTime": 508.28,
    "endTime": 510.199,
    "text": "left are gray"
  },
  {
    "startTime": 510.199,
    "endTime": 512.399,
    "text": "the seven yellow tiles on the right are"
  },
  {
    "startTime": 512.399,
    "endTime": 516.039,
    "text": "also gray they are the same okay don't"
  },
  {
    "startTime": 516.039,
    "endTime": 518.839,
    "text": "believe me let's watch it"
  },
  {
    "startTime": 518.839,
    "endTime": 522.039,
    "text": "again what's true for color is also true"
  },
  {
    "startTime": 522.039,
    "endTime": 524.72,
    "text": "for complex perceptions of motion so"
  },
  {
    "startTime": 524.72,
    "endTime": 530.32,
    "text": "here we have let's turn this around a"
  },
  {
    "startTime": 530.32,
    "endTime": 532.8,
    "text": "diamond and what I'm going to do is I'm"
  },
  {
    "startTime": 532.8,
    "endTime": 534.32,
    "text": "going to hold it here and I'm going to"
  },
  {
    "startTime": 534.32,
    "endTime": 536.2,
    "text": "spin"
  },
  {
    "startTime": 536.2,
    "endTime": 538.279,
    "text": "it and for all of you you'll see it"
  },
  {
    "startTime": 538.279,
    "endTime": 540.279,
    "text": "probably spinning this direction"
  },
  {
    "startTime": 540.279,
    "endTime": 542.959,
    "text": "now I want you to keep looking at it"
  },
  {
    "startTime": 542.959,
    "endTime": 544.959,
    "text": "move your eyes around blink maybe close"
  },
  {
    "startTime": 544.959,
    "endTime": 546.8,
    "text": "one eye and suddenly it'll flip and"
  },
  {
    "startTime": 546.8,
    "endTime": 548.36,
    "text": "start spinning the opposite"
  },
  {
    "startTime": 548.36,
    "endTime": 551.16,
    "text": "direction yes raise your hand if you got"
  },
  {
    "startTime": 551.16,
    "endTime": 553.839,
    "text": "that yes keep blinking every time you"
  },
  {
    "startTime": 553.839,
    "endTime": 557.0,
    "text": "blink it'll switch right so I can ask"
  },
  {
    "startTime": 557.0,
    "endTime": 559.48,
    "text": "you which direction is it"
  },
  {
    "startTime": 559.48,
    "endTime": 561.44,
    "text": "rotating how do you"
  },
  {
    "startTime": 561.44,
    "endTime": 564.0,
    "text": "know your brain doesn't know because"
  },
  {
    "startTime": 564.0,
    "endTime": 566.32,
    "text": "both are equally likely so depending on"
  },
  {
    "startTime": 566.32,
    "endTime": 568.36,
    "text": "where it looks it flips between the two"
  },
  {
    "startTime": 568.36,
    "endTime": 570.48,
    "text": "possibilities"
  },
  {
    "startTime": 570.48,
    "endTime": 572.399,
    "text": "are we the only ones that see Illusions"
  },
  {
    "startTime": 572.399,
    "endTime": 574.8,
    "text": "the answer to this question is no even"
  },
  {
    "startTime": 574.8,
    "endTime": 577.6,
    "text": "the beautiful Bumblebee with its mere 1"
  },
  {
    "startTime": 577.6,
    "endTime": 579.92,
    "text": "million brain cells which is 250 times"
  },
  {
    "startTime": 579.92,
    "endTime": 581.959,
    "text": "fewer cells when you have one retina"
  },
  {
    "startTime": 581.959,
    "endTime": 584.48,
    "text": "sees Illusions does the most complicated"
  },
  {
    "startTime": 584.48,
    "endTime": 586.2,
    "text": "things that even our most sophisticated"
  },
  {
    "startTime": 586.2,
    "endTime": 588.44,
    "text": "computers can't do so in my lab we of"
  },
  {
    "startTime": 588.44,
    "endTime": 590.04,
    "text": "course work on bumblebees because we can"
  },
  {
    "startTime": 590.04,
    "endTime": 591.44,
    "text": "completely control their experience and"
  },
  {
    "startTime": 591.44,
    "endTime": 592.92,
    "text": "see how that alters the architecture of"
  },
  {
    "startTime": 592.92,
    "endTime": 594.399,
    "text": "their brain and we do this in what we"
  },
  {
    "startTime": 594.399,
    "endTime": 597.24,
    "text": "call the B Matrix and here you have the"
  },
  {
    "startTime": 597.24,
    "endTime": 598.68,
    "text": "hive you can see the queen bee that"
  },
  {
    "startTime": 598.68,
    "endTime": 600.0,
    "text": "large be in the middle there those are"
  },
  {
    "startTime": 600.0,
    "endTime": 601.88,
    "text": "all her daughters the eggs and they go"
  },
  {
    "startTime": 601.88,
    "endTime": 604.519,
    "text": "back and forth between this Hive and the"
  },
  {
    "startTime": 604.519,
    "endTime": 607.36,
    "text": "arena VI this"
  },
  {
    "startTime": 608.12,
    "endTime": 610.36,
    "text": "tube and you'll see one of the bees come"
  },
  {
    "startTime": 610.36,
    "endTime": 612.72,
    "text": "out here you see she has a little number"
  },
  {
    "startTime": 612.72,
    "endTime": 613.399,
    "text": "on"
  },
  {
    "startTime": 613.399,
    "endTime": 615.48,
    "text": "her yeah there's another one coming out"
  },
  {
    "startTime": 615.48,
    "endTime": 618.0,
    "text": "she also has a number on her now they're"
  },
  {
    "startTime": 618.0,
    "endTime": 621.16,
    "text": "not born that way right we pull them out"
  },
  {
    "startTime": 621.16,
    "endTime": 622.36,
    "text": "put them in the fridge and they fall"
  },
  {
    "startTime": 622.36,
    "endTime": 623.6,
    "text": "asleep and then you can super glut"
  },
  {
    "startTime": 623.6,
    "endTime": 625.64,
    "text": "little numbers on them"
  },
  {
    "startTime": 625.64,
    "endTime": 627.72,
    "text": "right and now in this experiment they"
  },
  {
    "startTime": 627.72,
    "endTime": 628.959,
    "text": "get a reward if they go to the blue"
  },
  {
    "startTime": 628.959,
    "endTime": 631.16,
    "text": "flower flowers okay and they land on the"
  },
  {
    "startTime": 631.16,
    "endTime": 633.0,
    "text": "flower they stick their tongue in there"
  },
  {
    "startTime": 633.0,
    "endTime": 634.56,
    "text": "called the prosus and they drink sugar"
  },
  {
    "startTime": 634.56,
    "endTime": 636.2,
    "text": "water now she's drinking a glass of"
  },
  {
    "startTime": 636.2,
    "endTime": 638.079,
    "text": "water that's about that big to you and I"
  },
  {
    "startTime": 638.079,
    "endTime": 640.639,
    "text": "we'll do that about three times and then"
  },
  {
    "startTime": 640.639,
    "endTime": 643.399,
    "text": "fly"
  },
  {
    "startTime": 643.399,
    "endTime": 645.88,
    "text": "right and sometimes they learn not to go"
  },
  {
    "startTime": 645.88,
    "endTime": 647.519,
    "text": "to the blue but to go to where the other"
  },
  {
    "startTime": 647.519,
    "endTime": 649.959,
    "text": "bees go so they copy each other they can"
  },
  {
    "startTime": 649.959,
    "endTime": 651.92,
    "text": "count to five they can recognize faces"
  },
  {
    "startTime": 651.92,
    "endTime": 654.0,
    "text": "and here she comes down the ladder and"
  },
  {
    "startTime": 654.0,
    "endTime": 655.6,
    "text": "she'll come into the hive find an empty"
  },
  {
    "startTime": 655.6,
    "endTime": 658.8,
    "text": "honey pot and throw up and that's honey"
  },
  {
    "startTime": 658.8,
    "endTime": 661.959,
    "text": "okay now"
  },
  {
    "startTime": 662.0,
    "endTime": 664.04,
    "text": "remember she's supposed to be going to"
  },
  {
    "startTime": 664.04,
    "endTime": 665.6,
    "text": "the blue flowers but what are these bees"
  },
  {
    "startTime": 665.6,
    "endTime": 667.36,
    "text": "doing in the upper right corner it looks"
  },
  {
    "startTime": 667.36,
    "endTime": 668.959,
    "text": "like they're going to green"
  },
  {
    "startTime": 668.959,
    "endTime": 672.56,
    "text": "flowers now are they getting it wrong"
  },
  {
    "startTime": 672.56,
    "endTime": 673.88,
    "text": "and the answer to the question is no"
  },
  {
    "startTime": 673.88,
    "endTime": 676.12,
    "text": "those are actually blue flowers but"
  },
  {
    "startTime": 676.12,
    "endTime": 679.6,
    "text": "those are blue flowers under green light"
  },
  {
    "startTime": 679.6,
    "endTime": 681.2,
    "text": "so they're using the relationships"
  },
  {
    "startTime": 681.2,
    "endTime": 683.399,
    "text": "between the colors to solve the puzzle"
  },
  {
    "startTime": 683.399,
    "endTime": 686.72,
    "text": "which is exactly what we do so Illusions"
  },
  {
    "startTime": 686.72,
    "endTime": 689.639,
    "text": "are often used especially in art by in"
  },
  {
    "startTime": 689.639,
    "endTime": 691.519,
    "text": "the words of a more contemporary artist"
  },
  {
    "startTime": 691.519,
    "endTime": 693.079,
    "text": "to demonstrate the fragility of our"
  },
  {
    "startTime": 693.079,
    "endTime": 695.88,
    "text": "senses okay this is complete rubbish"
  },
  {
    "startTime": 695.88,
    "endTime": 697.839,
    "text": "okay the senses aren't fragile if they"
  },
  {
    "startTime": 697.839,
    "endTime": 700.839,
    "text": "were we wouldn't be here okay instead"
  },
  {
    "startTime": 700.839,
    "endTime": 702.839,
    "text": "color tells us something completely"
  },
  {
    "startTime": 702.839,
    "endTime": 704.12,
    "text": "different that the brain didn't actually"
  },
  {
    "startTime": 704.12,
    "endTime": 706.959,
    "text": "evolve to see the world the way it is we"
  },
  {
    "startTime": 706.959,
    "endTime": 709.68,
    "text": "can't instead the brain evolved to see"
  },
  {
    "startTime": 709.68,
    "endTime": 711.48,
    "text": "the world the way it was useful to see"
  },
  {
    "startTime": 711.48,
    "endTime": 714.959,
    "text": "in the past and how we see is by"
  },
  {
    "startTime": 714.959,
    "endTime": 719.279,
    "text": "continually redefining normality"
  },
  {
    "startTime": 720.6,
    "endTime": 724.079,
    "text": "so how can we take this incredible"
  },
  {
    "startTime": 724.079,
    "endTime": 726.8,
    "text": "capacity of of plasticity of the brain"
  },
  {
    "startTime": 726.8,
    "endTime": 728.44,
    "text": "and get people to experience their world"
  },
  {
    "startTime": 728.44,
    "endTime": 730.079,
    "text": "differently well one of the ways we do"
  },
  {
    "startTime": 730.079,
    "endTime": 733.56,
    "text": "in my lab and studio is we translate the"
  },
  {
    "startTime": 733.56,
    "endTime": 736.199,
    "text": "light into sound and we enable people to"
  },
  {
    "startTime": 736.199,
    "endTime": 739.6,
    "text": "hear their visual World okay and they"
  },
  {
    "startTime": 739.6,
    "endTime": 741.76,
    "text": "can navigate the world using their"
  },
  {
    "startTime": 741.76,
    "endTime": 744.519,
    "text": "ears here's David in the right and he's"
  },
  {
    "startTime": 744.519,
    "endTime": 747.079,
    "text": "holding a camera on the left is what his"
  },
  {
    "startTime": 747.079,
    "endTime": 748.519,
    "text": "camera sees and you'll see there's a"
  },
  {
    "startTime": 748.519,
    "endTime": 750.36,
    "text": "line a faint line going across that"
  },
  {
    "startTime": 750.36,
    "endTime": 752.399,
    "text": "image that line is broken up to 32"
  },
  {
    "startTime": 752.399,
    "endTime": 754.72,
    "text": "squares and each Square we calculate the"
  },
  {
    "startTime": 754.72,
    "endTime": 756.279,
    "text": "average color and then we just simply"
  },
  {
    "startTime": 756.279,
    "endTime": 758.48,
    "text": "translate that into sound and now he's"
  },
  {
    "startTime": 758.48,
    "endTime": 759.279,
    "text": "going"
  },
  {
    "startTime": 759.279,
    "endTime": 763.0,
    "text": "to turn around close his"
  },
  {
    "startTime": 763.0,
    "endTime": 766.04,
    "text": "eyes and find a plate on the ground with"
  },
  {
    "startTime": 766.04,
    "endTime": 769.48,
    "text": "his eyes closed"
  },
  {
    "startTime": 770.67,
    "endTime": 785.36,
    "text": "[Music]"
  },
  {
    "startTime": 785.88,
    "endTime": 788.519,
    "text": "he finds it amazing right so not only"
  },
  {
    "startTime": 788.519,
    "endTime": 789.839,
    "text": "can we create a prosthetic for the"
  },
  {
    "startTime": 789.839,
    "endTime": 791.92,
    "text": "visually impaired but we can also"
  },
  {
    "startTime": 791.92,
    "endTime": 793.839,
    "text": "investigate investigate how people"
  },
  {
    "startTime": 793.839,
    "endTime": 796.399,
    "text": "literally make sense of the world but we"
  },
  {
    "startTime": 796.399,
    "endTime": 798.399,
    "text": "can also do something else we can also"
  },
  {
    "startTime": 798.399,
    "endTime": 801.68,
    "text": "make music with color so working with"
  },
  {
    "startTime": 801.68,
    "endTime": 805.32,
    "text": "kids they created images thinking about"
  },
  {
    "startTime": 805.32,
    "endTime": 807.279,
    "text": "what might the image of sound like if we"
  },
  {
    "startTime": 807.279,
    "endTime": 809.12,
    "text": "could listen to them and then we"
  },
  {
    "startTime": 809.12,
    "endTime": 811.079,
    "text": "translated these images and this is one"
  },
  {
    "startTime": 811.079,
    "endTime": 813.44,
    "text": "of those images and this is a 6-year-old"
  },
  {
    "startTime": 813.44,
    "endTime": 815.88,
    "text": "child composing a piece of music for a"
  },
  {
    "startTime": 815.88,
    "endTime": 817.12,
    "text": "32-piece"
  },
  {
    "startTime": 817.12,
    "endTime": 819.16,
    "text": "Orchestra and this is what it sounds"
  },
  {
    "startTime": 819.16,
    "endTime": 821.94,
    "text": "like"
  },
  {
    "startTime": 821.94,
    "endTime": 834.08,
    "text": "[Music]"
  },
  {
    "startTime": 834.08,
    "endTime": 838.889,
    "text": "[Applause]"
  },
  {
    "startTime": 840.47,
    "endTime": 846.8,
    "text": "[Music]"
  },
  {
    "startTime": 846.8,
    "endTime": 850.199,
    "text": "so a six-year-old child okay now what"
  },
  {
    "startTime": 850.199,
    "endTime": 852.0,
    "text": "does all this"
  },
  {
    "startTime": 852.0,
    "endTime": 854.44,
    "text": "mean what this suggests is that no one"
  },
  {
    "startTime": 854.44,
    "endTime": 857.399,
    "text": "is an outside Observer of nature okay"
  },
  {
    "startTime": 857.399,
    "endTime": 858.839,
    "text": "we're not defined by our essential"
  },
  {
    "startTime": 858.839,
    "endTime": 861.04,
    "text": "Properties by the bits that make us up"
  },
  {
    "startTime": 861.04,
    "endTime": 863.6,
    "text": "we're defined by our environment and our"
  },
  {
    "startTime": 863.6,
    "endTime": 865.68,
    "text": "interaction with that environment bi"
  },
  {
    "startTime": 865.68,
    "endTime": 869.079,
    "text": "ecology and that ecology is NE"
  },
  {
    "startTime": 869.079,
    "endTime": 871.72,
    "text": "necessarily relative historical and"
  },
  {
    "startTime": 871.72,
    "endTime": 876.04,
    "text": "empirical right so what I'd like to"
  },
  {
    "startTime": 876.04,
    "endTime": 878.959,
    "text": "finish with is this over here because"
  },
  {
    "startTime": 878.959,
    "endTime": 880.16,
    "text": "what I've been trying to do is really"
  },
  {
    "startTime": 880.16,
    "endTime": 881.72,
    "text": "celebrate uncertainty because I think"
  },
  {
    "startTime": 881.72,
    "endTime": 883.44,
    "text": "only through uncertainty is their"
  },
  {
    "startTime": 883.44,
    "endTime": 885.759,
    "text": "potential for understanding so if some"
  },
  {
    "startTime": 885.759,
    "endTime": 887.56,
    "text": "of you are still feeling a bit too"
  },
  {
    "startTime": 887.56,
    "endTime": 891.0,
    "text": "certain I'd like to do this one so if we"
  },
  {
    "startTime": 891.0,
    "endTime": 895.6,
    "text": "have the lights down and what we"
  },
  {
    "startTime": 895.6,
    "endTime": 897.639,
    "text": "have"
  },
  {
    "startTime": 897.639,
    "endTime": 902.04,
    "text": "here can everyone see 25 purple surfaces"
  },
  {
    "startTime": 902.04,
    "endTime": 906.12,
    "text": "on your left and 25 call it yellowish"
  },
  {
    "startTime": 906.12,
    "endTime": 908.24,
    "text": "surfaces on your right so now what I'm"
  },
  {
    "startTime": 908.24,
    "endTime": 910.04,
    "text": "going to do I'm going to put the middle"
  },
  {
    "startTime": 910.04,
    "endTime": 913.12,
    "text": "nine surfaces here under yellow"
  },
  {
    "startTime": 913.12,
    "endTime": 914.839,
    "text": "illumination by simply putting a filter"
  },
  {
    "startTime": 914.839,
    "endTime": 916.44,
    "text": "behind"
  },
  {
    "startTime": 916.44,
    "endTime": 919.12,
    "text": "them all right now you can see that"
  },
  {
    "startTime": 919.12,
    "endTime": 921.12,
    "text": "changes the light that's coming through"
  },
  {
    "startTime": 921.12,
    "endTime": 922.88,
    "text": "there right because now the light's"
  },
  {
    "startTime": 922.88,
    "endTime": 925.48,
    "text": "going through a yellowish filter and"
  },
  {
    "startTime": 925.48,
    "endTime": 927.24,
    "text": "then a purplish filter and I'm going to"
  },
  {
    "startTime": 927.24,
    "endTime": 931.199,
    "text": "do this opposite on on the left here I'm"
  },
  {
    "startTime": 931.199,
    "endTime": 935.04,
    "text": "going to put the middle nine under a"
  },
  {
    "startTime": 935.04,
    "endTime": 940.44,
    "text": "purplish light okay now some of you have"
  },
  {
    "startTime": 940.44,
    "endTime": 943.0,
    "text": "noticed that the consequence is that the"
  },
  {
    "startTime": 943.0,
    "endTime": 944.48,
    "text": "light coming through those middle nine"
  },
  {
    "startTime": 944.48,
    "endTime": 948.0,
    "text": "on the right or your left is exactly the"
  },
  {
    "startTime": 948.0,
    "endTime": 949.279,
    "text": "same as a light coming through the"
  },
  {
    "startTime": 949.279,
    "endTime": 954.24,
    "text": "middle line on your right agreed yes"
  },
  {
    "startTime": 954.24,
    "endTime": 956.88,
    "text": "okay so they are physically the same let"
  },
  {
    "startTime": 956.88,
    "endTime": 960.6,
    "text": "pull the covers off"
  },
  {
    "startTime": 962.319,
    "endTime": 964.56,
    "text": "now"
  },
  {
    "startTime": 965.0,
    "endTime": 967.8,
    "text": "remember you know that the middle nine"
  },
  {
    "startTime": 967.8,
    "endTime": 971.72,
    "text": "are exactly the same do they look the"
  },
  {
    "startTime": 971.72,
    "endTime": 975.68,
    "text": "same no question is is that an illusion"
  },
  {
    "startTime": 975.68,
    "endTime": 977.48,
    "text": "and I'll leave you with that so thank"
  },
  {
    "startTime": 977.48,
    "endTime": 980.88,
    "text": "you very much"
  },
  {
    "startTime": 981.02,
    "endTime": 984.32,
    "text": "[Applause]"
  },
  {
    "startTime": 989.6,
    "endTime": 993.12,
    "text": "traffic is a global epidemic us traffic"
  },
  {
    "startTime": 993.12,
    "endTime": 995.519,
    "text": "is creating 45% of the world's air"
  },
  {
    "startTime": 995.519,
    "endTime": 998.0,
    "text": "pollution in the UK time wasted in"
  },
  {
    "startTime": 998.0,
    "endTime": 1000.399,
    "text": "traffic costs 20 billion a year would"
  },
  {
    "startTime": 1000.399,
    "endTime": 1002.079,
    "text": "you pay for cleaner air and a faster"
  },
  {
    "startTime": 1002.079,
    "endTime": 1004.759,
    "text": "commute Stockholm put it to a vote I"
  },
  {
    "startTime": 1004.759,
    "endTime": 1008.199,
    "text": "voted for it yes I voted for it I vote"
  },
  {
    "startTime": 1008.199,
    "endTime": 1012.04,
    "text": "for it we're not old enough to vote"
  },
  {
    "startTime": 1012.04,
    "endTime": 1015.519,
    "text": "vote we had to do something in Stockholm"
  },
  {
    "startTime": 1015.519,
    "endTime": 1019.36,
    "text": "to improve the environment and to get a"
  },
  {
    "startTime": 1019.36,
    "endTime": 1022.079,
    "text": "better flow in the traffic we put a"
  },
  {
    "startTime": 1022.079,
    "endTime": 1024.48,
    "text": "price on taking your car into the"
  },
  {
    "startTime": 1024.48,
    "endTime": 1026.678,
    "text": "central parts of Stockholm and we call"
  },
  {
    "startTime": 1026.679,
    "endTime": 1028.48,
    "text": "that congestion"
  },
  {
    "startTime": 1028.48,
    "endTime": 1030.798,
    "text": "charges if you start a system like this"
  },
  {
    "startTime": 1030.799,
    "endTime": 1033.319,
    "text": "and it doesn't work on the first day"
  },
  {
    "startTime": 1033.319,
    "endTime": 1035.798,
    "text": "then you will be in big trouble it must"
  },
  {
    "startTime": 1035.799,
    "endTime": 1037.72,
    "text": "be perfect from day"
  },
  {
    "startTime": 1037.72,
    "endTime": 1041.079,
    "text": "one there are 18 entry gates to the city"
  },
  {
    "startTime": 1041.079,
    "endTime": 1043.319,
    "text": "each is equipped with cameras pictures"
  },
  {
    "startTime": 1043.319,
    "endTime": 1045.438,
    "text": "are taken of the rear and front license"
  },
  {
    "startTime": 1045.439,
    "endTime": 1048.038,
    "text": "plates these pictures are sent to a"
  },
  {
    "startTime": 1048.039,
    "endTime": 1050.2,
    "text": "central system that identifies the"
  },
  {
    "startTime": 1050.2,
    "endTime": 1052.16,
    "text": "license plates and makes sure that the"
  },
  {
    "startTime": 1052.16,
    "endTime": 1054.559,
    "text": "right person pays for the right passages"
  },
  {
    "startTime": 1054.559,
    "endTime": 1057.36,
    "text": "one of the obstacles we overcame was the"
  },
  {
    "startTime": 1057.36,
    "endTime": 1059.64,
    "text": "OCR the optical character reading of the"
  },
  {
    "startTime": 1059.64,
    "endTime": 1062.08,
    "text": "license plate we went out to IBM's"
  },
  {
    "startTime": 1062.08,
    "endTime": 1065.32,
    "text": "Global organization and the R&D centers"
  },
  {
    "startTime": 1065.32,
    "endTime": 1067.08,
    "text": "and find a very good software we could"
  },
  {
    "startTime": 1067.08,
    "endTime": 1069.12,
    "text": "use and we managed to implement it in"
  },
  {
    "startTime": 1069.12,
    "endTime": 1071.08,
    "text": "two months time this is the heart of the"
  },
  {
    "startTime": 1071.08,
    "endTime": 1073.12,
    "text": "system where all images and passages are"
  },
  {
    "startTime": 1073.12,
    "endTime": 1076.28,
    "text": "being processed over 99% of old pictures"
  },
  {
    "startTime": 1076.28,
    "endTime": 1079.32,
    "text": "are correctly identified"
  },
  {
    "startTime": 1079.32,
    "endTime": 1081.2,
    "text": "no it's nice this is how it should be"
  },
  {
    "startTime": 1081.2,
    "endTime": 1082.159,
    "text": "all the"
  },
  {
    "startTime": 1082.159,
    "endTime": 1084.919,
    "text": "time behind me you can see the traffic"
  },
  {
    "startTime": 1084.919,
    "endTime": 1087.28,
    "text": "and the clock is 6:00 p.m. before we had"
  },
  {
    "startTime": 1087.28,
    "endTime": 1088.96,
    "text": "the congesting charging the traffic was"
  },
  {
    "startTime": 1088.96,
    "endTime": 1092.48,
    "text": "chewing up at this time of the day just"
  },
  {
    "startTime": 1092.48,
    "endTime": 1095.28,
    "text": "idea I think it's a good idea because I"
  },
  {
    "startTime": 1095.28,
    "endTime": 1097.08,
    "text": "think that we should take care of the"
  },
  {
    "startTime": 1097.08,
    "endTime": 1099.76,
    "text": "environment in the city the traffic went"
  },
  {
    "startTime": 1099.76,
    "endTime": 1102.52,
    "text": "down with about 22% and the the air"
  },
  {
    "startTime": 1102.52,
    "endTime": 1105.48,
    "text": "pollution was about 14% better it's a"
  },
  {
    "startTime": 1105.48,
    "endTime": 1107.36,
    "text": "huge International interest from"
  },
  {
    "startTime": 1107.36,
    "endTime": 1109.64,
    "text": "different part of the world from uh the"
  },
  {
    "startTime": 1109.64,
    "endTime": 1112.84,
    "text": "United States from Latin America from"
  },
  {
    "startTime": 1112.84,
    "endTime": 1116.799,
    "text": "China and it's really pressure to tell"
  },
  {
    "startTime": 1116.799,
    "endTime": 1118.84,
    "text": "people not what we are planning to do"
  },
  {
    "startTime": 1118.84,
    "endTime": 1120.919,
    "text": "but what we actually have done in"
  },
  {
    "startTime": 1120.919,
    "endTime": 1123.919,
    "text": "Stockholm I voted for it yes I did not"
  },
  {
    "startTime": 1123.919,
    "endTime": 1127.559,
    "text": "my husband so but I did I think he is"
  },
  {
    "startTime": 1127.559,
    "endTime": 1131.28,
    "text": "not thinking like me for the future I'm"
  },
  {
    "startTime": 1131.28,
    "endTime": 1133.0,
    "text": "thinking for the children and the"
  },
  {
    "startTime": 1133.0,
    "endTime": 1136.0,
    "text": "grandchildren"
  },
  {
    "startTime": 1137.77,
    "endTime": 1141.13,
    "text": "[Music]"
  }
]