[
  {
    "startTime": 0.0,
    "endTime": 8.0,
    "text": "Of the many flavors of bad bosses out there, one of the most common and most painful to work for is the insecure manager."
  },
  {
    "startTime": 8.189,
    "endTime": 15.4,
    "text": "Insecure bosses can be nitpicky micro-managers or paranoid meddlers who make you question your every move."
  },
  {
    "startTime": 15.6,
    "endTime": 19.5,
    "text": "And if they see you as a threat, they may even try to damage your career."
  },
  {
    "startTime": 19.8,
    "endTime": 32.6,
    "text": "If you've ever doubted yourself because your boss doesn't have faith in you or shoots down your ideas without any explanation or blames you for their lack of success, this video is for you."
  },
  {
    "startTime": 32.8,
    "endTime": 35.4,
    "text": "So how do know if you're dealing with an insecure manager?"
  },
  {
    "startTime": 35.6,
    "endTime": 37.33,
    "text": "Here are some common traits."
  },
  {
    "startTime": 37.33,
    "endTime": 40.0,
    "text": "They're overly concerned about what others think of them."
  },
  {
    "startTime": 40.0,
    "endTime": 42.3,
    "text": "They can't make a decision or stick with one."
  },
  {
    "startTime": 42.5,
    "endTime": 48.7,
    "text": "They're always highlighting their own expertise or credentials, sometimes putting down others to make themselves feel better."
  },
  {
    "startTime": 48.9,
    "endTime": 53.5,
    "text": "They require that every decision in detail have their approval."
  },
  {
    "startTime": 53.7,
    "endTime": 61.400000000000006,
    "text": "They don't allow their team to interact with people from other departments or senior leaders in an attempt to control the flow of information."
  },
  {
    "startTime": 61.7,
    "endTime": 65.23,
    "text": "If you're working with someone who fits that description, what can you do?"
  },
  {
    "startTime": 65.23,
    "endTime": 71.47,
    "text": "It is so tempting to retaliate or to push back or confront them or even report them to their boss."
  },
  {
    "startTime": 71.47,
    "endTime": 73.0,
    "text": "But you shouldn't do that."
  },
  {
    "startTime": 73.0,
    "endTime": 76.15,
    "text": "It is likely to backfire big time."
  },
  {
    "startTime": 76.15,
    "endTime": 85.0,
    "text": "Once they sense that you have disdain for them or that you can't be trusted, they're likely to amp up their defensiveness, making your life more miserable."
  },
  {
    "startTime": 85.3,
    "endTime": 91.33,
    "text": "Instead, you want to start by understanding what might be causing their self-doubt."
  },
  {
    "startTime": 91.33,
    "endTime": 95.5,
    "text": "Let me just say, for the record, a certain amount of self-doubt is completely normal."
  },
  {
    "startTime": 95.7,
    "endTime": 101.38,
    "text": "At times, we all wonder if we can say nail that presentation or if our coworkers think we're smart."
  },
  {
    "startTime": 101.38,
    "endTime": 109.1,
    "text": "Insecurity crosses over into problematic behavior, however, when people try to conceal or compensate for their self-doubt."
  },
  {
    "startTime": 109.24,
    "endTime": 112.27,
    "text": "They end up resorting to the tactics I just outlined."
  },
  {
    "startTime": 112.27,
    "endTime": 118.5,
    "text": "This might surprise you, but research shows that people in positions of power are more prone to feelings of insecurity."
  },
  {
    "startTime": 118.7,
    "endTime": 120.5,
    "text": "Think about it-- all eyes are on them."
  },
  {
    "startTime": 120.7,
    "endTime": 122.4,
    "text": "They're under a lot of pressure."
  },
  {
    "startTime": 122.6,
    "endTime": 126.69999999999999,
    "text": "They may fear being outed as incompetent or even losing their position of power."
  },
  {
    "startTime": 126.9,
    "endTime": 130.6,
    "text": "Knowing that can help you reframe how you see their behavior."
  },
  {
    "startTime": 130.8,
    "endTime": 135.07000000000002,
    "text": "For example, you may instinctively think \"my boss wants to destroy my career.\""
  },
  {
    "startTime": 135.07,
    "endTime": 137.6,
    "text": "Or \"my manager wants everyone else to look bad.\""
  },
  {
    "startTime": 137.8,
    "endTime": 141.70000000000002,
    "text": "But go deeper, do they really want to destroy your career?"
  },
  {
    "startTime": 141.7,
    "endTime": 142.5,
    "text": "That's unlikely."
  },
  {
    "startTime": 142.7,
    "endTime": 147.39999999999998,
    "text": "More likely, they're nervous about losing their job, say, in an upcoming round of layoffs."
  },
  {
    "startTime": 147.4,
    "endTime": 155.4,
    "text": "Or they think that by criticizing you--sometimes harshly--they're going to motivate you to perform better, which will ultimately make them look better."
  },
  {
    "startTime": 155.6,
    "endTime": 159.2,
    "text": "OK, now that you have a better sense of their motives, let's improve the situation."
  },
  {
    "startTime": 159.4,
    "endTime": 161.5,
    "text": "Here are some tactics."
  },
  {
    "startTime": 161.7,
    "endTime": 163.5,
    "text": "Tactic 1, remain patient."
  },
  {
    "startTime": 163.7,
    "endTime": 169.5,
    "text": "Far too many bosses are overwhelmed, overextended, underqualified, and/or undertrained."
  },
  {
    "startTime": 169.7,
    "endTime": 178.2,
    "text": "It's quite possible that dealing with legitimate pressures, like hitting year-end targets or dealing with tough clients is causing them to take their insecurities out on you."
  },
  {
    "startTime": 178.39,
    "endTime": 180.13,
    "text": "So exercise empathy."
  },
  {
    "startTime": 180.13,
    "endTime": 181.29999999999998,
    "text": "Remain patient."
  },
  {
    "startTime": 181.5,
    "endTime": 183.5,
    "text": "Easier said than done, I know."
  },
  {
    "startTime": 183.7,
    "endTime": 184.6,
    "text": "But here's a tactic that's worked for others."
  },
  {
    "startTime": 185.8,
    "endTime": 190.5,
    "text": "Imagine your boss as a child who's completely unaware of the harm they're causing."
  },
  {
    "startTime": 190.7,
    "endTime": 195.5,
    "text": "That mental picture can help you keep your composure and stay calm."
  },
  {
    "startTime": 195.7,
    "endTime": 203.5,
    "text": "Here's another example, if your boss is riling you up, excuse yourself for a moment to take time to compose yourself and calm down."
  },
  {
    "startTime": 203.7,
    "endTime": 208.6,
    "text": "Controlling your anger can keep tensions down and allow you to do your job."
  },
  {
    "startTime": 208.8,
    "endTime": 212.44,
    "text": "Tactic 2, frame your work as a joint effort."
  },
  {
    "startTime": 212.44,
    "endTime": 221.0,
    "text": "Instead of competing with your insecure boss--pro tip, you're probably going to lose--figure out what their objectives are and how you can achieve them together."
  },
  {
    "startTime": 221.0,
    "endTime": 224.23,
    "text": "This is about framing things as a joint effort."
  },
  {
    "startTime": 224.23,
    "endTime": 227.0,
    "text": "Start sentences with \"we\" as much as possible."
  },
  {
    "startTime": 227.0,
    "endTime": 229.39,
    "text": "Try saying things like \"We've got this.\""
  },
  {
    "startTime": 229.39,
    "endTime": 231.6,
    "text": "Or \"It's good that we're in this together.\""
  },
  {
    "startTime": 231.8,
    "endTime": 234.4,
    "text": "And when you do succeed, share the glory."
  },
  {
    "startTime": 234.6,
    "endTime": 238.4,
    "text": "Don't in any way downplay your own efforts, but highlight the partnership."
  },
  {
    "startTime": 238.7,
    "endTime": 245.6,
    "text": "Acknowledging that you're on the same side can build trust and diffuse your boss's insecurities."
  },
  {
    "startTime": 245.8,
    "endTime": 248.47,
    "text": "Tactic 3, signal that you're not a threat."
  },
  {
    "startTime": 248.4,
    "endTime": 251.70000000000002,
    "text": "You want your boss to think of you as an ally, not a rival."
  },
  {
    "startTime": 251.9,
    "endTime": 253.6,
    "text": "It's best to do this at the beginning."
  },
  {
    "startTime": 253.8,
    "endTime": 257.35,
    "text": "But it's never too late to reset the tone of your relationship."
  },
  {
    "startTime": 257.35,
    "endTime": 262.48,
    "text": "The key is to watch what you say and do so they don't see you as even more of a threat."
  },
  {
    "startTime": 262.48,
    "endTime": 271.3,
    "text": "For example, saying something as simple as \"I don't understand that,\" can feel like a challenge to their intelligence even if you're genuinely curious what they're thinking."
  },
  {
    "startTime": 271.3,
    "endTime": 276.6,
    "text": "A better way to say \"I don't understand that,\" may be \"Help me understand your thinking.\""
  },
  {
    "startTime": 276.8,
    "endTime": 284.6,
    "text": "Or instead of saying \"Why are we doing it this way?\" try saying something like, \"Do you mind sharing your thinking here?\""
  },
  {
    "startTime": 284.8,
    "endTime": 288.04,
    "text": "Tactic 4, flattery works--as long as it's genuine."
  },
  {
    "startTime": 288.04,
    "endTime": 294.13,
    "text": "Research on managers who feel incompetent has shown that flattery--genuine flattery--really helps."
  },
  {
    "startTime": 294.13,
    "endTime": 297.4,
    "text": "Like everyone else, your boss needs positive feedback too."
  },
  {
    "startTime": 297.6,
    "endTime": 301.21000000000004,
    "text": "Many people worry about coming off as sycophants or suck-ups."
  },
  {
    "startTime": 301.21,
    "endTime": 302.04999999999995,
    "text": "I get it."
  },
  {
    "startTime": 302.05,
    "endTime": 306.5,
    "text": "If compliments are not your thing, just express appreciation for something they've done."
  },
  {
    "startTime": 306.7,
    "endTime": 311.2,
    "text": "Even saying \"thank you\" preferably in front of others can go a long way."
  },
  {
    "startTime": 311.2,
    "endTime": 317.182,
    "text": "You might thank them for giving you a high-profile project or making a connection for you in another department."
  },
  {
    "startTime": 317.0,
    "endTime": 322.06,
    "text": "Buttering up your boss when they're making your life miserable it's probably the last thing you want to do."
  },
  {
    "startTime": 322.06,
    "endTime": 323.23,
    "text": "But it's in your interest."
  },
  {
    "startTime": 323.23,
    "endTime": 327.20000000000005,
    "text": "It'll increase your influence and decrease your stress."
  },
  {
    "startTime": 327.3,
    "endTime": 329.40000000000003,
    "text": "Tactic 5, restore their sense of control."
  },
  {
    "startTime": 329.6,
    "endTime": 334.40000000000003,
    "text": "Insecure managers who have trouble trusting others often resort to micromanaging."
  },
  {
    "startTime": 334.6,
    "endTime": 339.28000000000003,
    "text": "You can interrupt some of their meddling by reassuring them that they're in charge."
  },
  {
    "startTime": 339.2,
    "endTime": 342.34,
    "text": "Your manager may be terrified of being out of the loop."
  },
  {
    "startTime": 342.34,
    "endTime": 345.07,
    "text": "So keep them up to date as much as possible."
  },
  {
    "startTime": 345.07,
    "endTime": 351.49,
    "text": "And be transparent about what you're working on and who you're talking to, especially if it's people in other parts of the company."
  },
  {
    "startTime": 351.49,
    "endTime": 356.24,
    "text": "Schedule regular check-ins to keep your boss updated on projects that they care about."
  },
  {
    "startTime": 356.24,
    "endTime": 358.42,
    "text": "Make them feel included in the process."
  },
  {
    "startTime": 358.42,
    "endTime": 363.46000000000004,
    "text": "Over-communicating now will save you the effort of defending yourself later."
  },
  {
    "startTime": 363.46,
    "endTime": 369.01,
    "text": "Another sneaky way to make them feel in control is to frame your suggestions as questions."
  },
  {
    "startTime": 369.01,
    "endTime": 375.5,
    "text": "Research shows that asking questions instead of giving answers boosts the sense of control in the other person."
  },
  {
    "startTime": 375.7,
    "endTime": 381.8,
    "text": "So pose questions that start with \"what if\" or \"could we\" then invite your manager to share their thoughts."
  },
  {
    "startTime": 382.0,
    "endTime": 391.9,
    "text": "Instead of saying something like, \"I think we should roll this initiative out in all of our markets,\" try saying, \"What if we rolled this initiative out in all of our markets? What would that take?\""
  },
  {
    "startTime": 392.02,
    "endTime": 402.29999999999995,
    "text": "Or instead of saying, \"It'd be better if we took a slower approach here.\" You could say, \"what if we built on your idea and tried to slow it down a bit?\""
  },
  {
    "startTime": 402.7,
    "endTime": 409.5,
    "text": "Unfortunately, no matter how strategic you are, it's unlikely that you're going to cure your manager of their insecurities."
  },
  {
    "startTime": 409.7,
    "endTime": 411.4,
    "text": "And that's not your responsibility."
  },
  {
    "startTime": 411.6,
    "endTime": 414.40000000000003,
    "text": "And ultimately, if all of these tactics fail,"
  },
  {
    "startTime": 414.7,
    "endTime": 420.19,
    "text": "you may need to figure out how to set up boundaries so you just interact with your boss less."
  },
  {
    "startTime": 420.19,
    "endTime": 421.36,
    "text": "Here's a quick recap."
  },
  {
    "startTime": 421.36,
    "endTime": 423.28000000000003,
    "text": "Don't retaliate or push back."
  },
  {
    "startTime": 423.28,
    "endTime": 426.4,
    "text": "Their anxieties are likely to ramp up, not calm down."
  },
  {
    "startTime": 426.7,
    "endTime": 431.5,
    "text": "Try to understand what pressures your manager is under or what's causing their insecurity."
  },
  {
    "startTime": 431.7,
    "endTime": 434.59999999999997,
    "text": "Position yourself as an ally, not a rival."
  },
  {
    "startTime": 434.8,
    "endTime": 439.48,
    "text": "Pay your boss genuine complements or express gratitude and appreciation."
  },
  {
    "startTime": 439.48,
    "endTime": 442.5,
    "text": "Start sentences with \"we\" as much as possible."
  },
  {
    "startTime": 442.7,
    "endTime": 447.3,
    "text": "Keep them updated and be transparent about what you're working on and who you're talking with."
  },
  {
    "startTime": 447.5,
    "endTime": 452.02,
    "text": "And schedule regular check-ins where you can share progress on projects your boss cares about."
  },
  {
    "startTime": 451.9,
    "endTime": 454.7,
    "text": "And make them feel included in your work."
  },
  {
    "startTime": 454.7,
    "endTime": 455.59999999999997,
    "text": "Thank you for watching."
  },
  {
    "startTime": 455.8,
    "endTime": 461.90000000000003,
    "text": "All of the tactics in this video are taken from my book \"Getting Along, How to Work with Anyone-- Even Difficult People.\""
  },
  {
    "startTime": 462.1,
    "endTime": 466.40000000000003,
    "text": "If you've worked with an insecure manager and you have a tactic to share, comment below."
  },
  {
    "startTime": 466.7,
    "endTime": 470.3,
    "text": "Also, let us know if you have a topic you want us to cover in an upcoming video."
  },
  {
    "startTime": 470.5,
    "endTime": 472.38,
    "text": "Bye for now."
  }
]