[
  {
    "startTime": 0.433,
    "endTime": 7.3999999999999995,
    "text": "♪ ♪"
  },
  {
    "startTime": 7.4,
    "endTime": 9.0,
    "text": "♪ FIRST THINGS FIRST ♪"
  },
  {
    "startTime": 9.0,
    "endTime": 11.565999999999999,
    "text": "♪ I'M GONNA SAY ALL THE WORDS INSIDE MY HEAD ♪"
  },
  {
    "startTime": 11.566,
    "endTime": 15.566,
    "text": "♪ I'M FIRED UP AND TIRED OF THE WAY THAT THINGS HAVE BEEN ♪"
  },
  {
    "startTime": 15.566,
    "endTime": 17.633000000000003,
    "text": "♪ OH WOO ♪"
  },
  {
    "startTime": 17.633,
    "endTime": 19.465999999999998,
    "text": "♪ THE WAY THAT THINGS HAVE BEEN ♪"
  },
  {
    "startTime": 19.466,
    "endTime": 22.5,
    "text": "♪ OH OOH ♪"
  },
  {
    "startTime": 22.5,
    "endTime": 24.133,
    "text": "♪ SECOND THINGS SECOND ♪"
  },
  {
    "startTime": 24.133,
    "endTime": 27.099999999999998,
    "text": "♪ DON'T YOU TELL ME WHAT YOU THINK THAT I COULD BE ♪"
  },
  {
    "startTime": 27.1,
    "endTime": 31.033,
    "text": "♪ I'M THE ONE AT THE SAIL, I'M THE MASTER OF MY SEA ♪"
  },
  {
    "startTime": 31.033,
    "endTime": 33.1,
    "text": "♪ OH OOH ♪"
  },
  {
    "startTime": 33.1,
    "endTime": 34.733000000000004,
    "text": "♪ THE MASTER OF MY SEA ♪"
  },
  {
    "startTime": 34.733,
    "endTime": 37.666,
    "text": "♪ OH OOH ♪"
  },
  {
    "startTime": 37.666,
    "endTime": 39.565999999999995,
    "text": "♪ I WAS BROKEN FROM A YOUNG AGE ♪"
  },
  {
    "startTime": 39.566,
    "endTime": 41.433,
    "text": "♪ TAKEN MY SULKING TO THE MASSES ♪"
  },
  {
    "startTime": 41.433,
    "endTime": 43.333,
    "text": "♪ WRITING MY POEMS FOR THE FEW ♪"
  },
  {
    "startTime": 43.333,
    "endTime": 45.166,
    "text": "♪ THAT LOOKED AT ME, TOOK TO ME, SHOOK TO ME, FEELING ME ♪"
  },
  {
    "startTime": 45.166,
    "endTime": 47.233,
    "text": "♪ SINGING FROM HEARTACHE FROM THE PAIN ♪"
  },
  {
    "startTime": 47.233,
    "endTime": 49.132999999999996,
    "text": "♪ TAKING MY MESSAGE FROM THE VEINS ♪"
  },
  {
    "startTime": 49.133,
    "endTime": 51.066,
    "text": "♪ SPEAKING MY LESSON FROM THE BRAIN ♪"
  },
  {
    "startTime": 51.066,
    "endTime": 54.366,
    "text": "♪ SEEING THE BEAUTY THROUGH THE ♪"
  },
  {
    "startTime": 54.366,
    "endTime": 55.633,
    "text": "♪ PAIN ♪"
  },
  {
    "startTime": 55.633,
    "endTime": 62.1,
    "text": "♪ YOU MADE ME A, YOU MADE ME A BELIEVER, BELIEVER ♪"
  },
  {
    "startTime": 62.1,
    "endTime": 63.566,
    "text": "♪ PAIN ♪"
  },
  {
    "startTime": 63.566,
    "endTime": 68.766,
    "text": "♪ YOU BREAK ME DOWN, YOU BUILD ME UP BELIEVER, BELIEVER ♪"
  },
  {
    "startTime": 68.766,
    "endTime": 70.60000000000001,
    "text": "♪ PAIN ♪"
  },
  {
    "startTime": 70.6,
    "endTime": 74.366,
    "text": "♪ LET THE BULLETS FLY OH LET THEM RAIN ♪"
  },
  {
    "startTime": 74.366,
    "endTime": 77.4,
    "text": "♪ MY LIFE, MY LOVE, MY DRIVE, IT CAME FROM ♪"
  },
  {
    "startTime": 77.4,
    "endTime": 78.66600000000001,
    "text": "♪ PAIN ♪"
  },
  {
    "startTime": 78.666,
    "endTime": 84.2,
    "text": "♪ YOU MADE ME A, YOU MADE ME A BELIEVER, BELIEVER ♪"
  },
  {
    "startTime": 84.2,
    "endTime": 85.46600000000001,
    "text": "♪ THIRD THINGS THIRD ♪"
  },
  {
    "startTime": 85.466,
    "endTime": 88.43299999999999,
    "text": "♪ SEND A PRAYER TO THE ONES UP ABOVE ♪"
  },
  {
    "startTime": 88.433,
    "endTime": 92.30000000000001,
    "text": "♪ ALL THE HATE THAT YOU'VE HEARD HAS TURNED YOUR SPIRIT TO A DOVE ♪"
  },
  {
    "startTime": 92.3,
    "endTime": 94.39999999999999,
    "text": "♪ OH OOO ♪"
  },
  {
    "startTime": 94.4,
    "endTime": 96.16600000000001,
    "text": "♪ YOUR SPIRIT UP ABOVE ♪"
  },
  {
    "startTime": 96.166,
    "endTime": 99.166,
    "text": "♪ OH OOO ♪"
  },
  {
    "startTime": 99.166,
    "endTime": 100.76599999999999,
    "text": "♪ I WAS CHOKING IN THE CROWD ♪"
  },
  {
    "startTime": 100.766,
    "endTime": 102.766,
    "text": "♪ BUILDING MY RAIN UP IN THE CLOUD ♪"
  },
  {
    "startTime": 102.766,
    "endTime": 104.66600000000001,
    "text": "♪ FALLING LIKE ASHES TO THE GROUND ♪"
  },
  {
    "startTime": 104.666,
    "endTime": 106.633,
    "text": "♪ HOPING MY FEELINGS, THEY WOULD DROWN ♪"
  },
  {
    "startTime": 106.633,
    "endTime": 108.76599999999999,
    "text": "♪ BUT THEY NEVER DID, EVER LIVED, EBBING AND FLOWING ♪"
  },
  {
    "startTime": 108.766,
    "endTime": 110.766,
    "text": "♪ INHIBITED, LIMITED, TILL IT BROKE OPEN ♪"
  },
  {
    "startTime": 110.766,
    "endTime": 115.63300000000001,
    "text": "♪ AND RAINED DOWN, YOU RAINED DOWN LIKE ♪"
  },
  {
    "startTime": 115.633,
    "endTime": 117.1,
    "text": "♪ PAIN ♪"
  },
  {
    "startTime": 117.1,
    "endTime": 123.466,
    "text": "♪ YOU MADE ME A, YOU MADE ME A BELIEVER, BELIEVER ♪"
  },
  {
    "startTime": 123.466,
    "endTime": 125.1,
    "text": "♪ PAIN ♪"
  },
  {
    "startTime": 125.1,
    "endTime": 130.13299999999998,
    "text": "♪ YOU BREAK ME DOWN YOU BUILD ME UP BELIEVER, BELIEVER ♪"
  },
  {
    "startTime": 130.133,
    "endTime": 132.066,
    "text": "♪ PAIN ♪"
  },
  {
    "startTime": 132.066,
    "endTime": 135.633,
    "text": "♪ LET THE BULLETS FLY, OH LET THEM RAIN ♪"
  },
  {
    "startTime": 135.633,
    "endTime": 138.76600000000002,
    "text": "♪ MY LIFE, MY LOVE, MY DRIVE, IT CAME FROM ♪"
  },
  {
    "startTime": 138.766,
    "endTime": 140.233,
    "text": "♪ PAIN ♪"
  },
  {
    "startTime": 140.233,
    "endTime": 145.366,
    "text": "♪ YOU MADE ME A, YOU MADE ME A BELIEVER, BELIEVER ♪"
  },
  {
    "startTime": 145.366,
    "endTime": 146.76600000000002,
    "text": "♪ LAST THINGS LAST ♪"
  },
  {
    "startTime": 146.766,
    "endTime": 149.7,
    "text": "♪ BY THE GRACE OF THE FIRE AND THE FLAME ♪"
  },
  {
    "startTime": 149.7,
    "endTime": 152.1,
    "text": "♪ YOU'RE THE FACE OF THE FUTURE ♪"
  },
  {
    "startTime": 152.1,
    "endTime": 153.7,
    "text": "♪ THE BLOOD IN MY VEINS ♪"
  },
  {
    "startTime": 153.7,
    "endTime": 155.766,
    "text": "♪ OH OOH ♪"
  },
  {
    "startTime": 155.766,
    "endTime": 157.5,
    "text": "♪ THE BLOOD IN MY VEINS ♪"
  },
  {
    "startTime": 157.5,
    "endTime": 160.433,
    "text": "♪ OH OOH ♪"
  },
  {
    "startTime": 160.433,
    "endTime": 162.566,
    "text": "♪ BUT THEY NEVER DID, EVER LIVED, EBBING AND FLOWING ♪"
  },
  {
    "startTime": 162.566,
    "endTime": 164.433,
    "text": "♪ INHIBITED, LIMITED, TILL IT BROKE OPEN ♪"
  },
  {
    "startTime": 164.433,
    "endTime": 173.5,
    "text": "♪ AND RAINED DOWN, YOU RAINED DOWN LIKE ♪"
  },
  {
    "startTime": 173.5,
    "endTime": 177.2,
    "text": "♪ I WANT TO STOP ♪"
  },
  {
    "startTime": 177.2,
    "endTime": 179.433,
    "text": "♪ WE CAN'T ♪"
  },
  {
    "startTime": 179.433,
    "endTime": 180.7,
    "text": "♪ PAIN ♪"
  },
  {
    "startTime": 180.7,
    "endTime": 187.2,
    "text": "♪ YOU MADE ME A, YOU MADE ME A BELIEVER, BELIEVER ♪"
  },
  {
    "startTime": 187.2,
    "endTime": 188.6,
    "text": "♪ PAIN ♪"
  },
  {
    "startTime": 188.6,
    "endTime": 194.066,
    "text": "♪ YOU BREAK ME DOWN YOU BUILD ME UP BELIEVER, BELIEVER ♪"
  },
  {
    "startTime": 194.066,
    "endTime": 195.666,
    "text": "♪ PAIN ♪"
  },
  {
    "startTime": 195.666,
    "endTime": 199.4,
    "text": "♪ LET THE BULLETS FLY OH LET THEM RAIN ♪"
  },
  {
    "startTime": 199.4,
    "endTime": 202.433,
    "text": "♪ MY LIFE MY LOVE MY DRIVE IT CAME FROM ♪"
  },
  {
    "startTime": 202.433,
    "endTime": 203.7,
    "text": "♪ PAIN ♪"
  },
  {
    "startTime": 203.7,
    "endTime": 213.7,
    "text": "♪ YOU MADE ME A, YOU MADE ME A BELIEVER, BELIEVER ♪"
  }
]