[
  {
    "startTime": 0.94,
    "endTime": 3.989,
    "text": "Yeah"
  },
  {
    "startTime": 3.99,
    "endTime": 7.33,
    "text": "Yeah, yeah"
  },
  {
    "startTime": 7.33,
    "endTime": 11.1,
    "text": "Yeah, yeah"
  },
  {
    "startTime": 11.1,
    "endTime": 13.2,
    "text": "Yeah, yeah"
  },
  {
    "startTime": 13.2,
    "endTime": 20.24,
    "text": "Yeah, yeah"
  },
  {
    "startTime": 20.24,
    "endTime": 22.779,
    "text": "Well, okay"
  },
  {
    "startTime": 22.78,
    "endTime": 25.18,
    "text": "I'm always sayin' I won't change but"
  },
  {
    "startTime": 25.18,
    "endTime": 26.36,
    "text": "I ain't the same"
  },
  {
    "startTime": 26.36,
    "endTime": 29.3,
    "text": "Everything is different, I can't complain"
  },
  {
    "startTime": 29.3,
    "endTime": 31.54,
    "text": "Don't know what you missing"
  },
  {
    "startTime": 31.54,
    "endTime": 32.98,
    "text": "Shame on you"
  },
  {
    "startTime": 32.98,
    "endTime": 34.589999999999996,
    "text": "Yeah, yeah, yeah"
  },
  {
    "startTime": 34.6,
    "endTime": 35.35,
    "text": "Shame on you"
  },
  {
    "startTime": 35.35,
    "endTime": 38.44,
    "text": "Everything is strange, that's just a game"
  },
  {
    "startTime": 38.44,
    "endTime": 41.46,
    "text": "Everybody tripping, throwing it away"
  },
  {
    "startTime": 41.46,
    "endTime": 44.45,
    "text": "We was getting lifted, now we getting paid"
  },
  {
    "startTime": 44.45,
    "endTime": 48.11,
    "text": "Shame on you"
  },
  {
    "startTime": 48.11,
    "endTime": 50.97,
    "text": "I pay the cost to see apostrophes"
  },
  {
    "startTime": 50.97,
    "endTime": 54.879,
    "text": "That means it's mine, keep to myself, taking my time"
  },
  {
    "startTime": 54.88,
    "endTime": 57.510000000000005,
    "text": "Always into some bullshit, and out of line"
  },
  {
    "startTime": 57.51,
    "endTime": 60.879,
    "text": "Driving with my eyes close, missing all the signs"
  },
  {
    "startTime": 60.88,
    "endTime": 63.650000000000006,
    "text": "Turn the ignition, I'm driven and sitting pretty"
  },
  {
    "startTime": 63.65,
    "endTime": 67.2,
    "text": "Listening to Whitney and whipping it through the city yeah"
  },
  {
    "startTime": 67.2,
    "endTime": 69.729,
    "text": "Man on a mission, figure it out"
  },
  {
    "startTime": 69.73,
    "endTime": 73.11,
    "text": "Putting way too much on my shoulders, please hold me down"
  },
  {
    "startTime": 73.11,
    "endTime": 74.98,
    "text": "I keep my head above the water (Water)"
  },
  {
    "startTime": 74.98,
    "endTime": 77.99000000000001,
    "text": "My eyes is getting bigger, so the world is getting smaller (Smaller)"
  },
  {
    "startTime": 77.99,
    "endTime": 80.8,
    "text": "I've been getting richer but that only made me crazy"
  },
  {
    "startTime": 80.8,
    "endTime": 83.899,
    "text": "Mama told me I was different even when I was a baby"
  },
  {
    "startTime": 83.9,
    "endTime": 87.62,
    "text": "That Mercedes through the PA when I pull up, sounded like a concert"
  },
  {
    "startTime": 87.62,
    "endTime": 91.34,
    "text": "Or a, or a monster truck, I'm tripping but I'm falling up"
  },
  {
    "startTime": 91.34,
    "endTime": 94.39,
    "text": "I always said I want it all, but it's not enough"
  },
  {
    "startTime": 94.39,
    "endTime": 96.5,
    "text": "O-kay"
  },
  {
    "startTime": 96.5,
    "endTime": 98.24,
    "text": "I'm always saying I won't change but"
  },
  {
    "startTime": 98.24,
    "endTime": 99.21,
    "text": "I ain't the same"
  },
  {
    "startTime": 99.21,
    "endTime": 102.5,
    "text": "Everything is different, I can't complain"
  },
  {
    "startTime": 102.5,
    "endTime": 104.73,
    "text": "Don't know what you missing"
  },
  {
    "startTime": 104.73,
    "endTime": 106.18,
    "text": "Shame on you"
  },
  {
    "startTime": 106.18,
    "endTime": 107.5,
    "text": "Yeah, yeah, yeah"
  },
  {
    "startTime": 107.5,
    "endTime": 108.52,
    "text": "Shame on you"
  },
  {
    "startTime": 108.52,
    "endTime": 111.52,
    "text": "Everything is strange, that's just a game"
  },
  {
    "startTime": 111.52,
    "endTime": 114.72,
    "text": "Everybody tripping, throwing it away"
  },
  {
    "startTime": 114.72,
    "endTime": 117.69,
    "text": "We was getting lifted, now we getting paid"
  },
  {
    "startTime": 117.69,
    "endTime": 119.58,
    "text": "Shame on you"
  },
  {
    "startTime": 119.58,
    "endTime": 125.66,
    "text": "We only just begun"
  },
  {
    "startTime": 125.66,
    "endTime": 131.75,
    "text": "No, we don't wanna hurt your feelings"
  },
  {
    "startTime": 131.75,
    "endTime": 138.11,
    "text": "I was only just begun"
  },
  {
    "startTime": 138.11,
    "endTime": 142.46,
    "text": "No, we don't wanna"
  },
  {
    "startTime": 142.46,
    "endTime": 143.21,
    "text": "Hurt (Hurt)"
  },
  {
    "startTime": 143.21,
    "endTime": 146.48000000000002,
    "text": "Feelings (Feelings)"
  },
  {
    "startTime": 146.48,
    "endTime": 148.869,
    "text": "Down go the system, long live the king"
  },
  {
    "startTime": 148.87,
    "endTime": 151.89000000000001,
    "text": "Turn the power off and get your water from the spring"
  },
  {
    "startTime": 151.89,
    "endTime": 155.39999999999998,
    "text": "I'm bringing everyone with me when shit get iffy"
  },
  {
    "startTime": 155.4,
    "endTime": 157.29,
    "text": "I give a hundred and fifty percent"
  },
  {
    "startTime": 157.29,
    "endTime": 160.32899999999998,
    "text": "'This, this shit that I'm dealing with, but wish I forget"
  },
  {
    "startTime": 160.33,
    "endTime": 162.15,
    "text": "Used to be feeling depressed,"
  },
  {
    "startTime": 162.15,
    "endTime": 164.37,
    "text": "Now that I'm living and I'm feeling obsessed"
  },
  {
    "startTime": 164.37,
    "endTime": 167.21,
    "text": "Yes, high in Jacuzzi's I been hitting the jets"
  },
  {
    "startTime": 167.21,
    "endTime": 170.45000000000002,
    "text": "I'm showing her some love she been giving me sex"
  },
  {
    "startTime": 170.45,
    "endTime": 171.35,
    "text": "Bless bless bless"
  },
  {
    "startTime": 171.35,
    "endTime": 176.239,
    "text": "Respect the outline, don't fuck around and be a victim of your pride"
  },
  {
    "startTime": 176.24,
    "endTime": 177.69,
    "text": "Why you lying? (Why you lying?)"
  },
  {
    "startTime": 177.69,
    "endTime": 179.94,
    "text": "Tell the truth and step aside"
  },
  {
    "startTime": 179.94,
    "endTime": 182.7,
    "text": "I don't got the time to let it slide (Yep)"
  },
  {
    "startTime": 182.7,
    "endTime": 186.19,
    "text": "I'm too grounded, push whips, that move mountains"
  },
  {
    "startTime": 186.2,
    "endTime": 187.64999999999998,
    "text": "New crib, blue fountains"
  },
  {
    "startTime": 187.65,
    "endTime": 189.38,
    "text": "These are my surroundings"
  },
  {
    "startTime": 189.38,
    "endTime": 191.76,
    "text": "I've been going through it, you just go around it"
  },
  {
    "startTime": 191.76,
    "endTime": 193.929,
    "text": "But it's really not that different when you think about it"
  },
  {
    "startTime": 193.93,
    "endTime": 195.64000000000001,
    "text": "I'm always saying I won't change but"
  },
  {
    "startTime": 195.64,
    "endTime": 196.88,
    "text": "I ain't the same"
  },
  {
    "startTime": 196.88,
    "endTime": 199.85,
    "text": "Everything is different, I can't complain"
  },
  {
    "startTime": 199.85,
    "endTime": 202.16,
    "text": "Don't know what you missing"
  },
  {
    "startTime": 202.16,
    "endTime": 203.77,
    "text": "Shame on you"
  },
  {
    "startTime": 203.77,
    "endTime": 204.53,
    "text": "Yeah, yeah, yeah"
  },
  {
    "startTime": 204.53,
    "endTime": 205.91,
    "text": "Shame on you"
  },
  {
    "startTime": 205.91,
    "endTime": 209.2,
    "text": "Everything is strange, that's just a game"
  },
  {
    "startTime": 209.2,
    "endTime": 212.39999999999998,
    "text": "Everybody tripping, throwing it away"
  },
  {
    "startTime": 212.4,
    "endTime": 215.16,
    "text": "We was getting lifted, now we getting paid"
  },
  {
    "startTime": 215.16,
    "endTime": 240.13,
    "text": "Shame on you"
  },
  {
    "startTime": 240.13,
    "endTime": 241.43,
    "text": "Hurt"
  },
  {
    "startTime": 241.43,
    "endTime": 245.64000000000001,
    "text": "Feelings"
  }
]